itmcp/__init__.py
itmcp/executor.py
mseep_itmcp-0.1.4.dist-info/licenses/LICENSE
pandoras_shell/executor.py
mseep_itmcp-0.1.4.dist-info/METADATA
mseep_itmcp-0.1.4.dist-info/WHEEL
mseep_itmcp-0.1.4.dist-info/top_level.txt
mseep_itmcp-0.1.4.dist-info/RECORD
