Metadata-Version: 2.4
Name: mseep-itmcp
Version: 0.1.4
Summary: MCP server enabling AI assistants to execute terminal commands through a secure shell interface
Author-email: mseep <support@skydeck.ai>
License-Expression: MIT
Requires-Python: >=3.10
License-File: LICENSE
Requires-Dist: mcp>=1.0.0
Dynamic: license-file
